py115/__about__.py
py115/__init__.py
py115/cloud.py
py115/py.typed
py115/types.py
py115/_internal/__init__.py
py115/_internal/oss.py
py115/_internal/compat/__init__.py
py115/_internal/crypto/__init__.py
py115/_internal/crypto/_rsa.py
py115/_internal/crypto/_xor.py
py115/_internal/crypto/ec115.py
py115/_internal/crypto/hash.py
py115/_internal/crypto/m115.py
py115/lowlevel/__init__.py
py115/lowlevel/_utils.py
py115/lowlevel/exceptions.py
py115/lowlevel/spec.py
py115/lowlevel/api/__init__.py
py115/lowlevel/api/_base.py
py115/lowlevel/api/_error.py
py115/lowlevel/api/app.py
py115/lowlevel/api/dir.py
py115/lowlevel/api/download.py
py115/lowlevel/api/file.py
py115/lowlevel/api/label.py
py115/lowlevel/api/media.py
py115/lowlevel/api/offline.py
py115/lowlevel/api/qrcode.py
py115/lowlevel/api/storage.py
py115/lowlevel/api/upload.py
py115/lowlevel/api/user.py
py115/lowlevel/client/__init__.py
py115/lowlevel/client/_base.py
py115/lowlevel/client/_client.py
py115/lowlevel/client/_cookie.py
py115/lowlevel/types/__init__.py
py115/lowlevel/types/app.py
py115/lowlevel/types/common.py
py115/lowlevel/types/dir.py
py115/lowlevel/types/download.py
py115/lowlevel/types/file.py
py115/lowlevel/types/label.py
py115/lowlevel/types/media.py
py115/lowlevel/types/offline.py
py115/lowlevel/types/qrcode.py
py115/lowlevel/types/storage.py
py115/lowlevel/types/upload.py
py115/lowlevel/types/user.py
py115-0.1.1.dist-info/METADATA
py115-0.1.1.dist-info/WHEEL
py115-0.1.1.dist-info/licenses/LICENSE
py115-0.1.1.dist-info/RECORD
