Metadata-Version: 2.3
Name: py115
Version: 0.1.1
Summary: Python SDK for 115 cloud storage service.
Project-URL: Homepage, https://github.com/deadblue/py115
Project-URL: Documentation, https://py115.readthedocs.io/en/latest/
Author-email: deadblue <public@dead.blue>
License: MIT License
Keywords: 115,cloud-storage,sdk
Classifier: Development Status :: 3 - Alpha
Classifier: License :: OSI Approved :: MIT License
Classifier: Operating System :: OS Independent
Classifier: Programming Language :: Python :: 3 :: Only
Classifier: Programming Language :: Python :: 3.10
Classifier: Programming Language :: Python :: 3.11
Classifier: Programming Language :: Python :: 3.12
Classifier: Programming Language :: Python :: 3.13
Classifier: Topic :: Software Development :: Libraries
Requires-Python: >=3.10
Requires-Dist: httpx>=0.27.0
Requires-Dist: lz4>=4.0.0
Requires-Dist: pycryptodome>=3.17.0
